autodiffpy/__init__.py
autodiffpy/autodiff.py
autodiffpy/autodiff_math.py
autodiffpy/autodiffmod.py
tests/__init__.py
tests/autodiff_math_test.py
tests/autodiff_test.py
autodiffpy-1.2.8.dist-info/LICENSE
autodiffpy-1.2.8.dist-info/METADATA
autodiffpy-1.2.8.dist-info/WHEEL
autodiffpy-1.2.8.dist-info/top_level.txt
autodiffpy-1.2.8.dist-info/RECORD
