Metadata-Version: 2.1
Name: autodiffpy
Version: 1.2.8
Summary: Autodifferentiation software package
Home-page: https://github.com/rajayuco/cs207-FinalProject
Author: Rachel Moon, Cory Williams, Yudi Wang, Jamila Pegues
Author-email: rachelmoon@g.harvard.edu, cwilliams@g.harvard.edu, yudiwang@g.harvard.edu, jpegues@g.harvard.edu
License: UNKNOWN
Platform: UNKNOWN
Classifier: Programming Language :: Python :: 3
Classifier: Operating System :: OS Independent
